CHANGELOG.rst
LICENSE
MANIFEST.in
README.rst
setup.py
service_factory/__init__.py
service_factory/compat.py
service_factory/errors.py
service_factory/exceptions.py
service_factory/factory.py
service_factory/service.py
service_factory/validation.py
service_factory.egg-info/PKG-INFO
service_factory.egg-info/SOURCES.txt
service_factory.egg-info/dependency_links.txt
service_factory.egg-info/not-zip-safe
service_factory.egg-info/top_level.txt
service_factory/providers/__init__.py
service_factory/providers/basehttp.py