Metadata-Version: 1.2
Name: service-factory
Version: 0.1.6
Summary: JSON RPC service factory for Python.
Home-page: https://github.com/proofit404/service-factory
Author: Artem Malyshev
Author-email: proofit404@gmail.com
Maintainer: Artem Malyshev
Maintainer-email: proofit404@gmail.com
License: GPL3
Platform: any
Classifier: Development Status :: 4 - Beta
Classifier: Intended Audience :: Developers
Classifier: License :: OSI Approved :: GNU General Public License v3 (GPLv3)
Classifier: Programming Language :: Python :: 2
Classifier: Programming Language :: Python :: 2.6
Classifier: Programming Language :: Python :: 2.7
Classifier: Programming Language :: Python :: 3
Classifier: Programming Language :: Python :: 3.3
Classifier: Programming Language :: Python :: 3.4
Classifier: Topic :: Software Development
